figurify/__init__.py
figurify/material_properties.py
figurify/units.py
figurify/figure_physics/__init__.py
figurify/figure_physics/dynamics.py
figurify/figure_physics/energy.py
figurify/figure_physics/forces.py
figurify/figure_physics/gravity.py
figurify/figure_physics/kinematics.py
figurify/figure_physics/momentum.py
figurify/geometric_solids/__init__.py
figurify/geometric_solids/cone.py
figurify/geometric_solids/cube.py
figurify/geometric_solids/cuboid.py
figurify/geometric_solids/cylinder.py
figurify/geometric_solids/prism.py
figurify/geometric_solids/pyramid.py
figurify/geometric_solids/sphere.py
figurify/geometric_solids/torus.py
figurify/plane_metrics/__init__.py
figurify/plane_metrics/circle.py
figurify/plane_metrics/ellipse.py
figurify/plane_metrics/parallelogram.py
figurify/plane_metrics/polygon.py
figurify/plane_metrics/quadrilateral.py
figurify/plane_metrics/rectangle.py
figurify/plane_metrics/trapezoid.py
figurify/plane_metrics/triangle.py
figurify-0.1.1.dist-info/LICENSE
figurify-0.1.1.dist-info/METADATA
figurify-0.1.1.dist-info/WHEEL
figurify-0.1.1.dist-info/top_level.txt
figurify-0.1.1.dist-info/RECORD
