Metadata-Version: 2.1
Name: figurify
Version: 0.1.1
Summary: With figurify you can calculate figures, surfaces and physics.
Author: Julian Hess
Project-URL: Source, https://github.com/julian-hess/Figurify.git
Classifier: Programming Language :: Python :: 3.11
Classifier: License :: OSI Approved :: MIT License
Classifier: Operating System :: OS Independent
Classifier: Intended Audience :: Developers
License-File: LICENSE
